getoutline_cli/__init__.py
getoutline_cli/getoutline_cli.py
getoutline_cli-0.4.2.dist-info/LICENSE
getoutline_cli-0.4.2.dist-info/METADATA
getoutline_cli-0.4.2.dist-info/WHEEL
getoutline_cli-0.4.2.dist-info/entry_points.txt
getoutline_cli-0.4.2.dist-info/top_level.txt
getoutline_cli-0.4.2.dist-info/RECORD
