Metadata-Version: 2.1
Name: getoutline-cli
Version: 0.4.2
Summary: CLI utility for publishing markdown files to Outline wiki
Home-page: https://github.com/bladerunner2020/getoutline-cli.git
Author: Alexander Pivovarov
Author-email: pivovarov@gmail.com
License: UNKNOWN
Project-URL: Bug Tracker, https://github.com/bladerunner2020/getoutline-cli/issues
Project-URL: Homepage, https://github.com/bladerunner2020/getoutline-cli#readme
Project-URL: Source, https://github.com/bladerunner2020/getoutline-cli
Platform: UNKNOWN
Classifier: Programming Language :: Python :: 3
Classifier: License :: OSI Approved :: MIT License
Classifier: Operating System :: OS Independent
Requires-Python: >=3.6
Requires-Dist: pyyaml
Requires-Dist: requests
Provides-Extra: dev
Requires-Dist: twine ; extra == 'dev'
Requires-Dist: wheel ; extra == 'dev'
Requires-Dist: flake8 ; extra == 'dev'
